{
  "closed": 47,
  "data": [
    {
      "id": "I_kwDOAffHH85M2vjV",
      "closed": false,
      "title": "Class-Balanced Loss based on Effectivene number of examples",
      "createdAt": "2022-06-30T00:02:58Z",
      "url": "https://github.com/keras-team/keras/issues/",
      "number": 16735,
      "assignees": {
        "nodes": [
          {
            "avatarUrl": "https://avatars.githubusercontent.com/u/20843596?u=6deb5872cde2e3ab5bf5d48ece503bc8b5b0bcf6&v=4",
            "name": "Ashutosh Hathidara",
            "url": "https://github.com/"
          },
          {
            "avatarUrl": "https://avatars.githubusercontent.com/u/78194266?u=1270684640732eaea36ac2d1725160fec0747089&v=4",
            "name": "divyasreepat",
            "url": "https://github.com/divyashreepathihalli"
          }
        ]
      },
      "repository": {
        "name": "keras",
        "url": "https://github.com/keras-team/keras",
        "owner": {
          "login": "keras-team",
          "avatarUrl": "https://avatars.githubusercontent.com/u/34455048?v=4",
          "url": "https://github.com/keras-team"
        }
      }
    }
  ],
  "open": 11,
  "totalCount": 58
}
